README.md
setup.py
SignatureSuper_Resolution.egg-info/PKG-INFO
SignatureSuper_Resolution.egg-info/SOURCES.txt
SignatureSuper_Resolution.egg-info/dependency_links.txt
SignatureSuper_Resolution.egg-info/top_level.txt
ssr/__init__.py
ssr/metric.py
ssr/utils.py
ssr/ssr_method/__init__.py
ssr/ssr_method/bezier_interpolation.py